spi_flash_controller.vhd
library IEEE;
use IEEE.STD_LOGIC_1164.ALL;
use IEEE.NUMERIC_STD.ALL;

entity spi_flash_controller is
    Port (
        clk         : in  std_logic;
        reset       : in  std_logic;
        start       : in  std_logic;
        data_in     : in  std_logic_vector(7 downto 0);
        data_out    : out std_logic_vector(7 downto 0);
        done_flag   : out std_logic;

        -- SPI signals
        spi_clk     : out std_logic;
        spi_mosi    : out std_logic;
        spi_miso    : in  std_logic;
        spi_cs      : out std_logic;

        -- Debug signal (internal shift register)
        shift_debug : out std_logic_vector(7 downto 0)
    );
end spi_flash_controller;

architecture Behavioral of spi_flash_controller is

    type state_type is (IDLE, ASSERT_CS, TRANSFER, STATE_DONE);
    signal state        : state_type := IDLE;

    signal clk_div_cnt  : integer := 0;
    constant CLK_DIV    : integer := 4;
    signal spi_clk_int  : std_logic := '0';

    signal bit_cnt      : integer range 0 to 7 := 0;
    signal shift_reg_tx : std_logic_vector(7 downto 0);
    signal shift_reg_rx : std_logic_vector(7 downto 0);

begin

    shift_debug <= shift_reg_rx;  -- assign debug output

    process(clk, reset)
    begin
        if reset = '1' then
            state <= IDLE;
            spi_cs <= '1';
            spi_clk_int <= '0';
            done_flag <= '0';
            spi_mosi <= '0';
        elsif rising_edge(clk) then

            -- Clock divider
            if clk_div_cnt = CLK_DIV then
                clk_div_cnt <= 0;
                spi_clk_int <= not spi_clk_int;
            else
                clk_div_cnt <= clk_div_cnt + 1;
            end if;

            case state is
                when IDLE =>
                    done_flag <= '0';
                    spi_cs <= '1';
                    if start = '1' then
                        shift_reg_tx <= data_in;
                        bit_cnt <= 7;
                        state <= ASSERT_CS;
                    end if;

                when ASSERT_CS =>
                    spi_cs <= '0';
                    state <= TRANSFER;

                when TRANSFER =>
                    if spi_clk_int = '0' then
                        spi_mosi <= shift_reg_tx(bit_cnt);  -- Drive data on falling edge
                    elsif spi_clk_int = '1' then
                        shift_reg_rx(bit_cnt) <= spi_miso;  -- Sample MISO on rising edge
                        if bit_cnt = 0 then
                            state <= STATE_DONE;
                        else
                            bit_cnt <= bit_cnt - 1;
                        end if;
                    end if;

                when STATE_DONE =>
                    data_out <= shift_reg_rx;
                    done_flag <= '1';
                    spi_cs <= '1';
                    state <= IDLE;
            end case;
        end if;
    end process;

    spi_clk <= spi_clk_int;

end Behavioral;

tb_spi_flash_controller.vhd
library IEEE;
use IEEE.STD_LOGIC_1164.ALL;
use IEEE.NUMERIC_STD.ALL;

entity tb_spi_flash_controller is
end tb_spi_flash_controller;

architecture sim of tb_spi_flash_controller is

    component spi_flash_controller
        Port (
            clk         : in  std_logic;
            reset       : in  std_logic;
            start       : in  std_logic;
            data_in     : in  std_logic_vector(7 downto 0);
            data_out    : out std_logic_vector(7 downto 0);
            done_flag   : out std_logic;
            spi_clk     : out std_logic;
            spi_mosi    : out std_logic;
            spi_miso    : in  std_logic;
            spi_cs      : out std_logic;
            shift_debug : out std_logic_vector(7 downto 0)
        );
    end component;

    -- Testbench signals
    signal clk         : std_logic := '0';
    signal reset       : std_logic := '1';
    signal start       : std_logic := '0';
    signal data_in     : std_logic_vector(7 downto 0) := x"A5";
    signal data_out    : std_logic_vector(7 downto 0);
    signal done_flag   : std_logic;
    signal spi_clk     : std_logic;
    signal spi_mosi    : std_logic;
    signal spi_miso    : std_logic := '1';  -- simulate '1's from slave
    signal spi_cs      : std_logic;
    signal shift_debug : std_logic_vector(7 downto 0);

    constant clk_period : time := 10 ns;

begin

    -- DUT instance
    uut: spi_flash_controller
        port map (
            clk         => clk,
            reset       => reset,
            start       => start,
            data_in     => data_in,
            data_out    => data_out,
            done_flag   => done_flag,
            spi_clk     => spi_clk,
            spi_mosi    => spi_mosi,
            spi_miso    => spi_miso,
            spi_cs      => spi_cs,
            shift_debug => shift_debug
        );

    -- Clock generation
    clk_process : process
    begin
        while true loop
            clk <= '0';
            wait for clk_period / 2;
            clk <= '1';
            wait for clk_period / 2;
        end loop;
    end process;

    -- Stimulus process
    stim_proc: process
    begin
        wait for 20 ns;
        reset <= '0';

        wait for 30 ns;
        start <= '1';
        wait for clk_period;
        start <= '0';

        wait until done_flag = '1';

        wait for 100 ns;
        assert false report "Simulation finished." severity failure;
    end process;

end sim;

spi.vcd
$date
  Sun Jun 29 14:36:04 2025
$end
$version
  GHDL v0
$end
$timescale
  1 fs
$end
$scope module standard $end
$upscope $end
$scope module std_logic_1164 $end
$upscope $end
$scope module numeric_std $end
$upscope $end
$scope module tb_spi_flash_controller $end
$var reg 1 ! clk $end
$var reg 1 " reset $end
$var reg 1 # start $end
$var reg 8 $ data_in[7:0] $end
$var reg 8 % data_out[7:0] $end
$var reg 1 & done_flag $end
$var reg 1 ' spi_clk $end
$var reg 1 ( spi_mosi $end
$var reg 1 ) spi_miso $end
$var reg 1 * spi_cs $end
$var reg 8 + shift_debug[7:0] $end
$scope module uut $end
$var reg 1 , clk $end
$var reg 1 - reset $end
$var reg 1 . start $end
$var reg 8 / data_in[7:0] $end
$var reg 8 0 data_out[7:0] $end
$var reg 1 1 done_flag $end
$var reg 1 2 spi_clk $end
$var reg 1 3 spi_mosi $end
$var reg 1 4 spi_miso $end
$var reg 1 5 spi_cs $end
$var reg 8 6 shift_debug[7:0] $end
$comment state is not handled $end
$var integer 32 7 clk_div_cnt $end
$var reg 1 8 spi_clk_int $end
$var integer 32 9 bit_cnt $end
$var reg 8 : shift_reg_tx[7:0] $end
$var reg 8 ; shift_reg_rx[7:0] $end
$upscope $end
$upscope $end
$enddefinitions $end
#0
0!
1"
0#
b10100101 $
bUUUUUUUU %
0&
0'
0(
1)
1*
bUUUUUUUU +
0,
1-
0.
b10100101 /
bUUUUUUUU 0
01
02
03
14
15
bUUUUUUUU 6
b0 7
08
b0 9
bUUUUUUUU :
bUUUUUUUU ;
#5000000
1!
1,
#10000000
0!
0,
#15000000
1!
1,
#20000000
0!
0"
0,
0-
#25000000
1!
1,
b1 7
#30000000
0!
0,
#35000000
1!
1,
b10 7
#40000000
0!
0,
#45000000
1!
1,
b11 7
#50000000
0!
1#
0,
1.
#55000000
1!
1,
b100 7
b111 9
b10100101 :
#60000000
0!
0#
0,
0.
#65000000
1!
1'
0*
1,
12
05
b0 7
18
#70000000
0!
0,
#75000000
1!
b1UUUUUUU +
1,
b1UUUUUUU 6
b1 7
b110 9
b1UUUUUUU ;
#80000000
0!
0,
#85000000
1!
b11UUUUUU +
1,
b11UUUUUU 6
b10 7
b101 9
b11UUUUUU ;
#90000000
0!
0,
#95000000
1!
b111UUUUU +
1,
b111UUUUU 6
b11 7
b100 9
b111UUUUU ;
#100000000
0!
0,
#105000000
1!
b1111UUUU +
1,
b1111UUUU 6
b100 7
b11 9
b1111UUUU ;
#110000000
0!
0,
#115000000
1!
0'
b11111UUU +
1,
02
b11111UUU 6
b0 7
08
b10 9
b11111UUU ;
#120000000
0!
0,
#125000000
1!
1(
1,
13
b1 7
#130000000
0!
0,
#135000000
1!
1,
b10 7
#140000000
0!
0,
#145000000
1!
1,
b11 7
#150000000
0!
0,
#155000000
1!
1,
b100 7
#160000000
0!
0,
#165000000
1!
1'
1,
12
b0 7
18
#170000000
0!
0,
#175000000
1!
b111111UU +
1,
b111111UU 6
b1 7
b1 9
b111111UU ;
#180000000
0!
0,
#185000000
1!
b1111111U +
1,
b1111111U 6
b10 7
b0 9
b1111111U ;
#190000000
0!
0,
#195000000
1!
b11111111 +
1,
b11111111 6
b11 7
b11111111 ;
#200000000
0!
0,
#205000000
1!
b11111111 %
1&
1*
1,
b11111111 0
11
15
b100 7
#210000000
0!
0,
#215000000
1!
0&
0'
1,
01
02
b0 7
08
#220000000
0!
0,
#225000000
1!
1,
b1 7
#230000000
0!
0,
#235000000
1!
1,
b10 7
#240000000
0!
0,
#245000000
1!
1,
b11 7
#250000000
0!
0,
#255000000
1!
1,
b100 7
#260000000
0!
0,
#265000000
1!
1'
1,
12
b0 7
18
#270000000
0!
0,
#275000000
1!
1,
b1 7
#280000000
0!
0,
#285000000
1!
1,
b10 7
#290000000
0!
0,
#295000000
1!
1,
b11 7
